centaurminer/DOM_elements.py
centaurminer/Engine.py
centaurminer/__init__.py
centaurminer/utils.py
centaurminer-0.1.0.dist-info/LICENSE
centaurminer-0.1.0.dist-info/METADATA
centaurminer-0.1.0.dist-info/WHEEL
centaurminer-0.1.0.dist-info/top_level.txt
centaurminer-0.1.0.dist-info/RECORD
