Metadata-Version: 2.1
Name: centaurminer
Version: 0.1.0
Summary: A selenium wrapper to help mining data from scientific literature.
Home-page: https://github.com/Simonsays095/CENTAURminer.git
Author: Simon Ewing
Author-email: Simonsays095@gmail.com
License: UNKNOWN
Project-URL: Documentation, https://centaurminer.readthedocs.io/
Project-URL: Source code, https://github.com/Simonsays095/CENTAURminer
Platform: UNKNOWN
Classifier: Programming Language :: Python :: 3
Classifier: License :: OSI Approved :: MIT License
Classifier: Operating System :: OS Independent
Classifier: Development Status :: 2 - Pre-Alpha
Classifier: Intended Audience :: Science/Research
Requires-Python: >=3.4
Requires-Dist: selenium
Requires-Dist: webdriver-manager
